aliyunsdkscsp/__init__.py
aliyunsdkscsp/endpoint.py
aliyunsdkscsp/request/__init__.py
aliyunsdkscsp/request/v20200702/AnswerCallRequest.py
aliyunsdkscsp/request/v20200702/AppMessagePushRequest.py
aliyunsdkscsp/request/v20200702/AssignTicketRequest.py
aliyunsdkscsp/request/v20200702/ChangeChatAgentStatusRequest.py
aliyunsdkscsp/request/v20200702/CloseTicketRequest.py
aliyunsdkscsp/request/v20200702/CreateAgentRequest.py
aliyunsdkscsp/request/v20200702/CreateCustomerRequest.py
aliyunsdkscsp/request/v20200702/CreateEntityIvrRouteRequest.py
aliyunsdkscsp/request/v20200702/CreateOuterCallCenterDataRequest.py
aliyunsdkscsp/request/v20200702/CreateRoleRequest.py
aliyunsdkscsp/request/v20200702/CreateSkillGroupRequest.py
aliyunsdkscsp/request/v20200702/CreateThirdSsoAgentRequest.py
aliyunsdkscsp/request/v20200702/CreateTicketRequest.py
aliyunsdkscsp/request/v20200702/CreateTicketWithBizDataRequest.py
aliyunsdkscsp/request/v20200702/DeleteAgentRequest.py
aliyunsdkscsp/request/v20200702/DeleteEntityRouteRequest.py
aliyunsdkscsp/request/v20200702/DisableRoleRequest.py
aliyunsdkscsp/request/v20200702/EditEntityRouteRequest.py
aliyunsdkscsp/request/v20200702/EnableRoleRequest.py
aliyunsdkscsp/request/v20200702/ExecuteActivityRequest.py
aliyunsdkscsp/request/v20200702/FetchCallRequest.py
aliyunsdkscsp/request/v20200702/FinishHotlineServiceRequest.py
aliyunsdkscsp/request/v20200702/GenerateWebSocketSignRequest.py
aliyunsdkscsp/request/v20200702/GetAgentRequest.py
aliyunsdkscsp/request/v20200702/GetAuthInfoRequest.py
aliyunsdkscsp/request/v20200702/GetCMSIdByForeignIdRequest.py
aliyunsdkscsp/request/v20200702/GetCallsPerDayRequest.py
aliyunsdkscsp/request/v20200702/GetEntityRouteListRequest.py
aliyunsdkscsp/request/v20200702/GetEntityRouteRequest.py
aliyunsdkscsp/request/v20200702/GetEntityTagRelationRequest.py
aliyunsdkscsp/request/v20200702/GetGrantedRoleIdsRequest.py
aliyunsdkscsp/request/v20200702/GetHotlineAgentDetailReportRequest.py
aliyun_python_sdk_scsp-1.0.0.dist-info/LICENSE
aliyun_python_sdk_scsp-1.0.0.dist-info/METADATA
aliyun_python_sdk_scsp-1.0.0.dist-info/WHEEL
aliyun_python_sdk_scsp-1.0.0.dist-info/top_level.txt
aliyun_python_sdk_scsp-1.0.0.dist-info/RECORD
